ppline
test
