Metadata-Version: 2.1
Name: ppline
Version: 0.2.5
Summary: Pipeline framework.
Home-page: https://github.com/5x12/ppline
Author: 5x12
License: MIT
Download-URL: https://github.com/5x12/ppline/archive/{version}.tar.gz
Keywords: PIPELINE,PIPE
Platform: UNKNOWN
Classifier: Development Status :: 3 - Alpha
Classifier: Intended Audience :: Developers
Classifier: License :: OSI Approved :: MIT License
Classifier: Programming Language :: Python :: 3.6
Requires-Python: >=3.6
License-File: LICENSE
